webcontentdownloader/__init__.py
webcontentdownloader/complexdownloader.py
webcontentdownloader/downloadmanager.py
webcontentdownloader/interface.py
webcontentdownloader/simpledownloader.py
webcontentdownloader/utils.py
webcontentdownloader-2.0.0.dist-info/LICENSE
webcontentdownloader-2.0.0.dist-info/METADATA
webcontentdownloader-2.0.0.dist-info/WHEEL
webcontentdownloader-2.0.0.dist-info/top_level.txt
webcontentdownloader-2.0.0.dist-info/RECORD
